ddcd/__init__.py
ddcd/ddcd_linear.py
ddcd/ddcd_nonlinear.py
ddcd/ddcd_smooth.py
ddcd/logger.py
ddcd/notears_denoising.py
ddcd/utils.py
ddcd/.ipynb_checkpoints/__init__-checkpoint.py
ddcd/.ipynb_checkpoints/ddcd_linear-checkpoint.py
ddcd/.ipynb_checkpoints/ddcd_nonlinear-checkpoint.py
ddcd/.ipynb_checkpoints/ddcd_smooth-checkpoint.py
ddcd/.ipynb_checkpoints/logger-checkpoint.py
ddcd/.ipynb_checkpoints/notears_denoising-checkpoint.py
ddcd/.ipynb_checkpoints/utils-checkpoint.py
ddcd-0.0.1.dist-info/WHEEL
ddcd-0.0.1.dist-info/METADATA
ddcd-0.0.1.dist-info/RECORD
