Metadata-Version: 2.4
Name: ddcd
Version: 0.0.1
Summary: Smoothing the Landscape: Causal Structure Learning via Diffusion Denoising Objectives
Author-email: Hao Zhu <haozhu233@gmail.com>
Maintainer-email: Hao Zhu <haozhu233@gmail.com>
License-Expression: MIT AND (Apache-2.0 OR BSD-2-Clause)
Classifier: Development Status :: 4 - Beta
Classifier: Programming Language :: Python :: 3
Requires-Dist: numpy>=1.16.5
Requires-Dist: pandas>=1.1.1
Requires-Dist: polars
Requires-Dist: torch
Requires-Dist: tqdm
Requires-Dist: scikit-learn
Requires-Dist: scipy
Project-URL: Home, https://github.com/haozhu233/ddcd
